{"version":1,"resource":"vscode-remote://ssh-remote%2Bdefault/home/vagrant/myproject/myapp/templates/appointmentspagesecretary.html","entries":[{"id":"5tzP.html","timestamp":1684679427723},{"id":"DJyJ.html","timestamp":1684679543103},{"id":"Wc0u.html","timestamp":1684679561131},{"id":"SBso.html","timestamp":1684680219523},{"id":"kpnb.html","timestamp":1684680520195},{"id":"1Z8H.html","timestamp":1684680640995},{"id":"TREb.html","timestamp":1684689312831},{"id":"FuA6.html","timestamp":1684985627837}]}